threatbus_misp/__init__.py
threatbus_misp/message_mapping.py
threatbus_misp/plugin.py
threatbus_misp/test_message_mapping.py
threatbus_misp-2022.5.16.dist-info/METADATA
threatbus_misp-2022.5.16.dist-info/WHEEL
threatbus_misp-2022.5.16.dist-info/entry_points.txt
threatbus_misp-2022.5.16.dist-info/top_level.txt
threatbus_misp-2022.5.16.dist-info/RECORD
