Metadata-Version: 2.1
Name: threatbus-misp
Version: 2022.5.16
Summary: A plugin to enable threatbus communication with MISP.
Home-page: https://github.com/tenzir/threatbus
Author: Tenzir
Author-email: engineering@tenzir.com
License: BSD 3-clause
Keywords: MISP,zeromq,zmq,kafka,threatbus,Threat Bus,threat intelligence,TI,TI dissemination
Platform: UNKNOWN
Classifier: Development Status :: 4 - Beta
Classifier: Environment :: Plugins
Classifier: License :: OSI Approved :: BSD License
Classifier: Operating System :: MacOS :: MacOS X
Classifier: Operating System :: POSIX :: Linux
Classifier: Programming Language :: Python :: 3
Classifier: Topic :: Scientific/Engineering :: Information Analysis
Classifier: Topic :: Scientific/Engineering :: Interface Engine/Protocol Translator
Classifier: Topic :: Security
Classifier: Topic :: Software Development :: Object Brokering
Classifier: Topic :: System :: Distributed Computing
Requires-Python: >=3.7
Requires-Dist: pymisp (>=2.4.120)
Requires-Dist: stix2 (>=3.0)
Requires-Dist: threatbus (>=2022.5.16)
Provides-Extra: kafka
Requires-Dist: confluent-kafka (>=1.3.0) ; extra == 'kafka'
Provides-Extra: zmq
Requires-Dist: pyzmq (>=18.1.1) ; extra == 'zmq'
